[
    {
        "symbol": "BTC",
        "title": "BTC Trades",
        "endpoints": [
            {
                "url": "/price_data",
                "type": "scatter"
            }
        ]
    },
    {
        "symbol": "BTC",
        "title": "BTC OHLCV",
        "endpoints": [
            {
                "url": "/ohlc_data",
                "type": "candlestick"
            }
        ]
    },
    {
        "symbol": "BTC",
        "title": "Trades density",
        "endpoints": [
            {
                "url": "/trades_density",
                "type": "scatter"
            }
        ]
    }
]
